odc/io/__init__.py
odc/io/_version.py
odc/io/cgroups.py
odc/io/tar.py
odc/io/text.py
odc/io/timer.py
odc_io-0.2.2.dist-info/LICENSE
odc_io-0.2.2.dist-info/METADATA
odc_io-0.2.2.dist-info/WHEEL
odc_io-0.2.2.dist-info/top_level.txt
odc_io-0.2.2.dist-info/RECORD
